<quizReport xmlns="http://www.ispringsolutions.com/ispring/quizbuilder/quizresults" xmlns:xsi="http://www.w3.org/2001/XMLSchema-instance" xsi:schemaLocation="http://www.ispringsolutions.com/ispring/quizbuilder/quizresults quizReport.xsd" version="1"><quizSettings quizType="survey" timeLimit="0"/><summary time="80"><variables><variable name="COMPANY" title="Название компании" value="КОМПАНИЯ РАНХИГС"/><variable name="USER_EMAIL" title="E-mail" value="dimacheg@ya.ru"/><variable name="PHONE" title="Телефон" value="9803011493"/></variables></summary><questions><pickOneQuestion id="{4EA86901-5D93-41FF-8752-62344DF46401}" status="answered"><direction>1.Каков статус Вашего бизнеса?
</direction><answers userAnswerIndex="0"><answer>Самозанятый гражданин
</answer><answer>Индивидуальный предприниматель
</answer><answer>Микропредприятие
</answer><answer>Малое предприятие
</answer><answer>Среднее предприятие
</answer></answers></pickOneQuestion><pickOneQuestion id="{D88324B2-6CD8-4C90-9EF3-5361FAA92FED}" status="answered"><direction>2.Где зарегистрировано Ваше предприятие?
</direction><answers userAnswerIndex="1"><answer>в Брянске
</answer><answer>в Москве
</answer><answer>в другом городе Российской Федерации
</answer><answer>за рубежом
</answer></answers></pickOneQuestion><pickOneQuestion id="{6F4D45B6-E894-4F8C-B114-327549A54CC8}" status="answered"><direction>3.Вид деятельности?
</direction><answers userAnswerIndex="5"><answer>торговля розничная
</answer><answer>оптовая торговля
</answer><answer>производство промышленных товаров
</answer><answer>производство потребительских товаров
</answer><answer>в сфере IT-технолог
</answer><answer customAnswer="своё">сфера услуг (укажите в какой отрасли)
</answer><answer>иное
</answer></answers></pickOneQuestion><pickOneQuestion id="{BF700675-806B-4077-962D-4E8761D96204}" status="answered"><direction>4.Удовлетворены ли Вы, как предприниматель, качеством развития административной среды для бизнеса в Брянске?
</direction><answers userAnswerIndex="3"><answer>Да, полностью. Учреждения, предоставляющие услуги, работают отлично, никаких проблем не возникает
</answer><answer>Скорее да, но есть проблемы с наличием административных барьеров в учреждениях, незаинтересованность персонала к решению моей проблемы
</answer><answer>Скорее нет, потому что приходится прикладывать много сил к решению проблем
</answer><answer>Нет, проблем много, нужно работать над качеством и сроками предоставления услуг
</answer></answers></pickOneQuestion><pickManyQuestion id="{A9F486E9-BB69-4456-AE60-C682FAE6D993}" status="answered"><direction>5.С какими контрольно-надзорными органами у вас возникают наибольшие трудности (выберите 2)?
</direction><answers><answer selected="false" originalIndex="0">налоговыми
</answer><answer selected="false" originalIndex="1">правоохранительными
</answer><answer selected="false" originalIndex="2">прокуратурой
</answer><answer selected="false" originalIndex="3">санэпидемнадзором
</answer><answer selected="false" originalIndex="4">технадзором
</answer><answer selected="false" originalIndex="5">природнадзором
</answer><answer selected="true" originalIndex="6">администрациями муниципалитетов
</answer><answer selected="true" originalIndex="7" customAnswer="иное">иное (укажите)
</answer></answers></pickManyQuestion><pickManyQuestion id="{72B4C4E1-B82A-4115-8928-478DA6E0D3D7}" status="answered"><direction>6.Какую сферу предпринимательства Вы считаете наиболее перспективной для развития в Брянске на ближайшие 10-15 лет (выберите не более 3-х)?
</direction><answers><answer selected="false" originalIndex="0">Торговля.
</answer><answer selected="false" originalIndex="1">Производство пищевой продукции (переработка продукции сельского хозяйства).
</answer><answer selected="false" originalIndex="2">Производство одежды и обуви, иных товаров повседневного спроса.Сфера развлечений.
</answer><answer selected="false" originalIndex="3">Бытовые услуги.
</answer><answer selected="false" originalIndex="4">Ресторанный, гостиничный бизнес, турфирмы.
</answer><answer selected="false" originalIndex="5">Финансовые услуги, операции с недвижимым имуществом, в т.ч. аренда.
</answer><answer selected="false" originalIndex="6">Сфера образования, здравоохранения.
</answer><answer selected="false" originalIndex="7">Информационные технологии (разработка, веб-дизайн, продвижение).
</answer><answer selected="false" originalIndex="8">Строительство.
</answer><answer selected="false" originalIndex="9">Транспортные услуги.
</answer><answer selected="true" originalIndex="10">Специализированные продукты и услуги (товары ручной работы и др.)
</answer><answer selected="true" originalIndex="11" customAnswer="своё">Другое
</answer></answers></pickManyQuestion><pickManyQuestion id="{11A1A1FA-120A-49EA-9F91-9B97416A734E}" status="answered"><direction>7.Что в первую очередь мешает  развитию предпринимательства в городе Брянске (выделите не более трёх наиболее существенных пунктов)?
</direction><answers><answer selected="false" originalIndex="0">Барьеры для входа на рынок.
</answer><answer selected="false" originalIndex="1">Низкий уровень образования работников.
</answer><answer selected="false" originalIndex="2">Неформальные связи на рынках сбыта.
</answer><answer selected="false" originalIndex="3">Высокие ставки по кредитам.
</answer><answer selected="false" originalIndex="4">Невозможность выхода на рынки других регионов и на зарубежные рынки.
</answer><answer selected="false" originalIndex="5">Высокие ставки аренды недвижимости.
</answer><answer selected="false" originalIndex="6">Высокая налоговая нагрузка.
</answer><answer selected="false" originalIndex="7">Дискриминация и предоставление преференций отдельным участникам на заведомо неравных условиях.
</answer><answer selected="false" originalIndex="8">Строительство.
</answer><answer selected="false" originalIndex="9">Рост числа проверок контролирующими органами.
</answer><answer selected="false" originalIndex="10">Давление на бизнес со стороны криминальных структур.
</answer><answer selected="false" originalIndex="11">Ограничение / сложность доступа к поставкам товаров, оказанию услуг и выполнению работ в рамках госзакупок/закупок госкомпаний.
</answer><answer selected="false" originalIndex="12">Сложность / затянутость процедуры получения лицензий.
</answer><answer selected="false" originalIndex="13">Высокая конкуренция со стороны компаний из других регионов и стран.
</answer><answer selected="false" originalIndex="14">Слабые меры господдержки бизнеса.
</answer><answer selected="false" originalIndex="15">Падение потребительского спроса.
</answer><answer selected="false" originalIndex="16">Сложность получения доступа к земельным участкам.
</answer><answer selected="true" originalIndex="17">Ничего не мешает, настоящий предприниматель всегда найдет выходы из любой ситуации.
</answer><answer selected="true" originalIndex="18" customAnswer="моё">Иное
</answer></answers></pickManyQuestion><pickManyQuestion id="{3797125C-4EEE-4F5A-9EED-53688F09CC37}" status="answered"><direction>8.Какие меры поддержки/стимулирования будут востребованы текущими и будущими предпринимателями?
</direction><answers><answer selected="false" originalIndex="0">Льготные кредиты предпринимателям, снижение ставок.
</answer><answer selected="false" originalIndex="1">Льготная аренда помещений, в том числе в коворкингах, бизнес-инкубаторах, технопарках.
</answer><answer selected="false" originalIndex="2">Снижение налоговой нагрузки для предпринимателей.
</answer><answer selected="false" originalIndex="3">Субсидии на модернизацию/на лизинг, покупку оборудования/на обучение кадров/на поддержку экспорта/на возмещение части затрат на уплату процентов по кредиту/на участие в выставках, ярмарках.
</answer><answer selected="false" originalIndex="4">Гранты начинающим предпринимателям на создание собственного дела.
</answer><answer selected="false" originalIndex="5">Отсутствие проверок, снижение административного давления.
</answer><answer selected="false" originalIndex="6">Снижение отчетности и бумажной волокиты.
</answer><answer selected="false" originalIndex="7">Возможность получать доступ к государственному заказу.
</answer><answer selected="false" originalIndex="8">Доступ к специализированным образовательным программам.
</answer><answer selected="false" originalIndex="9">Услуги акселерации стартапов.
</answer><answer selected="true" originalIndex="10">Услуги менторства (наставничества) для обучения поиску финансирования, рынков сбыта.
</answer><answer selected="true" originalIndex="11" customAnswer="яяя">Иное
</answer></answers></pickManyQuestion><pickOneQuestion id="{A8B76C86-2B8F-40AC-BA8A-18E5770C4011}" status="answered"><direction>9.Знаете ли Вы, где найти информацию о процессе регистрации юридического лица и ИП, о свободных арендных площадях, о мерах поддержки малого и среднего бизнеса в Брянске?
</direction><answers userAnswerIndex="3"><answer>Да, регулярно пользуюсь данными ресурсами/услугами организаций.
</answer><answer>Да, знаю, где искать, но ни разу не пользовался (лась) данными ресурсами/услугами организаций.
</answer><answer>Нет, нигде не видел(а) рекламы, хотя мне было бы интересно узнать побольше информации.
</answer><answer>Нет, пока не интересуюсь данным вопросом.
</answer></answers></pickOneQuestion><pickManyQuestion id="{55EA65A4-8E43-4097-995E-C2414D149820}" status="answered"><direction>10.Какими мерами поддержки Вы пользовались в течение последних трёх лет?
</direction><answers><answer selected="false" originalIndex="0">Размещение в Брянском областном бизнес-инкубаторе.
</answer><answer selected="false" originalIndex="1">Услуги Фонда поддержки малого и среднего предпринимательства Брянской области «Брянский Гарантийный Фонд».
</answer><answer selected="false" originalIndex="2">Услуги Фонда поддержки малого и среднего предпринимательства «Брянская Микрокредитная Компания».
</answer><answer selected="true" originalIndex="3">Услуги Банка МСП.
</answer><answer selected="true" originalIndex="4">Гранты начинающим субъектам малого предпринимательства.
</answer><answer selected="false" originalIndex="5">Участие в конференциях, выставках, ярмарках.
</answer><answer selected="false" originalIndex="6">Консультационная поддержка.
</answer><answer selected="false" originalIndex="7">Обучение и переобучение сотрудников.
</answer><answer selected="false" originalIndex="8">Не пользовался(лась) никакими.
</answer><answer selected="false" originalIndex="9">Иное (укажите)
</answer></answers></pickManyQuestion><pickManyQuestion id="{B10877A8-0594-48AB-A790-CC9453C5E7BB}" status="answered"><direction>11.Если бы Вы имели возможность определить приоритетную сферу в развитии экономики Брянска, Вы бы выбрали:
</direction><answers><answer selected="false" originalIndex="0">Промышленность.
</answer><answer selected="false" originalIndex="1">Транспорт.
</answer><answer selected="false" originalIndex="2">Торговля.
</answer><answer selected="false" originalIndex="3">Образование.
</answer><answer selected="false" originalIndex="4">Здравоохранение.
</answer><answer selected="false" originalIndex="5">Туризм.
</answer><answer selected="false" originalIndex="6">Все сферы имеют одинаковую значимость для развития экономики Брянска.
</answer><answer selected="true" originalIndex="7" customAnswer="яяяяяяяяяя">Другое
</answer></answers></pickManyQuestion><pickOneQuestion id="{AEC7CE4B-E630-4853-AC40-4D5528457096}" status="answered"><direction>12.Как Вы думаете, какой тип предприятий будет определять развитие экономика к 2030 году?
</direction><answers userAnswerIndex="3"><answer>Крупные международные промышленные группы.
</answer><answer>Крупные российские промышленные холдинги.
</answer><answer>Малые и средние инновационные компании.
</answer><answer>Средние быстрорастущие компании.
</answer></answers></pickOneQuestion><pickManyQuestion id="{9CB8A0DC-5697-48F4-9937-DA9488D24730}" status="answered"><direction>13.Экспорт каких товаров (услуг) Вы считаете наиболее перспективным для Брянска?
</direction><answers><answer selected="false" originalIndex="0">Промышленная продукция.
</answer><answer selected="false" originalIndex="1">Потребительские товары.
</answer><answer selected="false" originalIndex="2">Медицинские услуги.
</answer><answer selected="false" originalIndex="3">Туристические услуги.
</answer><answer selected="false" originalIndex="4">Услуги образования.
</answer><answer selected="false" originalIndex="5">Вся продукция (услуги) брянских компаний будет востребована зарубежными потребителями.
</answer><answer selected="false" originalIndex="6">Продукция (услуги) брянских компаний не конкурентоспособны на мировом рынке.
</answer><answer selected="true" originalIndex="7" customAnswer="товары">Другие товары.
</answer><answer selected="false" originalIndex="8">Не имею мнения по данному вопросу
</answer></answers></pickManyQuestion><pickOneQuestion id="{A38E9DA0-F288-42E6-B927-5AB301B57D13}" status="answered"><direction>14.Считаете ли Вы необходимым разработать экспортный бренд города Брянска?
</direction><answers userAnswerIndex="1"><answer>Да, бренд поможет местному бизнесу продвигать свою продукцию на мировом рынке.
</answer><answer>Нет, наличие бренда не повлияет на интерес зарубежных поставщиков и потребителей к региону.
</answer><answer>Не знаю, возможно, нужно использовать другие способы повышения узнаваемости продукции брянских производителей.
</answer></answers></pickOneQuestion><pickManyQuestion id="{55631D14-1D7F-46CD-9EFF-DA7B10F0DCA1}" status="answered"><direction>15.Если у Вас есть конструктивные предложения в адрес властей Брянска по развитию малого и среднего предпринимательства, пожалуйста сформулируйте их (до 200 знаков на каждое):
</direction><answers><answer selected="true" originalIndex="0" customAnswer="я">1
</answer><answer selected="true" originalIndex="1" customAnswer="2 пред">2
</answer><answer selected="true" originalIndex="2" customAnswer="3 пре">3
</answer></answers></pickManyQuestion><yesNoQuestion id="{FD546D79-959D-4F7C-BF08-2E8AB6B96345}" status="answered"><direction>16.Ваш пол:
</direction><answers userAnswerIndex="1"><answer>Женский
</answer><answer>Мужской
</answer></answers></yesNoQuestion><pickOneQuestion id="{2EAB4911-06B8-46F5-886D-C7EF00549A1E}" status="answered"><direction>17.Ваш возраст (полных лет):
</direction><answers userAnswerIndex="3"><answer>до 29 включительно
</answer><answer>30-39
</answer><answer>40-49
</answer><answer>50-59
</answer><answer>60 и старше
</answer></answers></pickOneQuestion><pickOneQuestion id="{24045742-F715-47B2-A538-3E9AA39BAF33}" status="answered"><direction>18.Ваше базовое образование:
</direction><answers userAnswerIndex="2"><answer>среднее (школа)
</answer><answer>начальное профессиональное (профтехучилище)
</answer><answer>среднее профессиональное (техникум, колледж)
</answer><answer>высшее
</answer></answers></pickOneQuestion></questions><groups/></quizReport>